tessbkgd/__init__.py
tessbkgd/tessbkgd.py
tessbkgd-0.2.1.dist-info/LICENSE
tessbkgd-0.2.1.dist-info/METADATA
tessbkgd-0.2.1.dist-info/WHEEL
tessbkgd-0.2.1.dist-info/top_level.txt
tessbkgd-0.2.1.dist-info/RECORD
